toomanythreads/__init__.py
toomanythreads/debug.py
toomanythreads/threaded_server.py
toomanythreads-0.2.77.dist-info/licenses/LICENSE
toomanythreads-0.2.77.dist-info/METADATA
toomanythreads-0.2.77.dist-info/WHEEL
toomanythreads-0.2.77.dist-info/top_level.txt
toomanythreads-0.2.77.dist-info/RECORD
