Metadata-Version: 2.4
Name: toomanythreads
Version: 0.2.77
Summary: A singleton-based thread management system
Author: Miles Copeland Luce
License: MIT
Keywords: threading,thread,management,singleton,decorator,async
Requires-Python: <4.0,>=3.13
License-File: LICENSE
Requires-Dist: loguru<0.8.0,>=0.7.3
Requires-Dist: singleton-decorator>=1.0.0
Requires-Dist: uvicorn<0.36.0,>=0.35.0
Requires-Dist: fastapi<0.117.0,>=0.116.1
Requires-Dist: toomanyports<0.2.0,>=0.1.1
Requires-Dist: starlette<0.48.0,>=0.47.2
Requires-Dist: httpx<0.29.0,>=0.28.1
Dynamic: license-file
